topicexplorer/__init__.py
topicexplorer/__main__.py
topicexplorer/cluster.py
topicexplorer/config.py
topicexplorer/debug.py
topicexplorer/demo.py
topicexplorer/etag.py
topicexplorer/export.py
topicexplorer/export_html.py
topicexplorer/init.py
topicexplorer/metadata.py
topicexplorer/notebook.py
topicexplorer/prep.py
topicexplorer/server.py
topicexplorer/tezimport.py
topicexplorer/train.py
topicexplorer/update.py
topicexplorer/version.py
topicexplorer/extensions/__init__.py
topicexplorer/extensions/ap.py
topicexplorer/extensions/bibtex.py
topicexplorer/extensions/htrc.py
topicexplorer/extensions/htrc_features.py
topicexplorer/extensions/inpho.py
topicexplorer/extensions/jeff.py
topicexplorer/extensions/jeffcombo.py
topicexplorer/extensions/oldbailey.py
topicexplorer/extensions/sep.py
topicexplorer/extensions/title.py
topicexplorer/lib/__init__.py
topicexplorer/lib/chinese.py
topicexplorer/lib/color.py
topicexplorer/lib/hathitrust.py
topicexplorer/lib/mmseg.py
topicexplorer/lib/pdf.py
topicexplorer/lib/ssl.py
topicexplorer/lib/util.py
topicexplorer/lib/win32.py
topicexplorer/tokenizer/__init__.py
topicexplorer-1.0b233.data/data/opt/topicexplorer/topics.zip
topicexplorer-1.0b233.data/data/opt/topicexplorer/demo/ap.md
topicexplorer-1.0b233.data/data/opt/topicexplorer/ipynb/Topic-Explorer-Tutorial.py2.ipynb
topicexplorer-1.0b233.data/data/opt/topicexplorer/ipynb/Topic-Explorer-Tutorial.py3.ipynb
topicexplorer-1.0b233.data/data/opt/topicexplorer/ipynb/corpus.tmpl.py
topicexplorer-1.0b233.data/data/opt/topicexplorer/mmseg/ancient_words.dic
topicexplorer-1.0b233.data/data/opt/topicexplorer/mmseg/chars.dic
topicexplorer-1.0b233.data/data/opt/topicexplorer/mmseg/modern_words.dic
topicexplorer-1.0b233.data/data/opt/topicexplorer/mmseg/words.dic
topicexplorer-1.0b233.data/data/opt/topicexplorer/www/.DS_Store
topicexplorer-1.0b233.data/data/opt/topicexplorer/www/bars.mustache.html
topicexplorer-1.0b233.data/data/opt/topicexplorer/www/bootstrap-tour.js
topicexplorer-1.0b233.dist-info/AUTHORS
topicexplorer-1.0b233.dist-info/LICENSE.txt
topicexplorer-1.0b233.dist-info/METADATA
topicexplorer-1.0b233.dist-info/WHEEL
topicexplorer-1.0b233.dist-info/entry_points.txt
topicexplorer-1.0b233.dist-info/pbr.json
topicexplorer-1.0b233.dist-info/top_level.txt
topicexplorer-1.0b233.dist-info/RECORD
