Metadata-Version: 2.1
Name: topicexplorer
Version: 1.0b233
Summary: InPhO Topic Explorer
Home-page: https://www.hypershelf.org
Download-URL: http://github.com/inpho/topic-explorer
Author: The Indiana Philosophy Ontology (InPhO) Project
Author-email: inpho@indiana.edu
Maintainer: Jaimie Murdock
Maintainer-email: jaimie@inphoproject.org
License: MIT License
Keywords: topic modeling,lda,visualization
Classifier: Programming Language :: Python
Classifier: Programming Language :: Python :: 2
Classifier: Programming Language :: Python :: 3
Classifier: Development Status :: 4 - Beta
Classifier: Environment :: Web Environment
Classifier: Framework :: Bottle
Classifier: Intended Audience :: Science/Research
Classifier: License :: OSI Approved :: MIT License
Classifier: Operating System :: OS Independent
Classifier: Topic :: Internet :: WWW/HTTP :: Dynamic Content
Classifier: Topic :: Scientific/Engineering :: Artificial Intelligence
Classifier: Topic :: Scientific/Engineering :: Visualization
Classifier: Topic :: Software Development :: User Interfaces
Classifier: Topic :: Text Processing :: Linguistic
License-File: LICENSE.txt
License-File: AUTHORS
Requires-Dist: bottle<0.13.0,>=0.12.0
Requires-Dist: brewer2mpl<1.5.0,>=1.4.0
Requires-Dist: decorator>=4.0.5
Requires-Dist: defusedxml>=0.7.1
Requires-Dist: future>=0.16.0
Requires-Dist: langdetect>=1.0.0
Requires-Dist: matplotlib>=2.0.0
Requires-Dist: mock>=2.0.0
Requires-Dist: nltk<4.0.0,>=3.0.0
Requires-Dist: notebook>=4.0.0
Requires-Dist: numpy<2.0.0
Requires-Dist: Paste==2.0.3
Requires-Dist: pdfminer.six==20170720
Requires-Dist: profilehooks>=1.8.0
Requires-Dist: progressbar2>=3.18.0
Requires-Dist: pybtex>=0.21
Requires-Dist: pystache>=0.5.4
Requires-Dist: requests>=2.14.2
Requires-Dist: scikit-learn>=0.18.1
Requires-Dist: scipy>=0.19.0
Requires-Dist: snakeviz>=0.4.0
Requires-Dist: sortedcontainers>=1.5.7
Requires-Dist: ujson>=1.35
Requires-Dist: Unidecode
Requires-Dist: vsm>=0.4.15
Requires-Dist: waitress>=1.0.0
Requires-Dist: webtest>=2.0.29
Requires-Dist: wget>=3.2
Requires-Dist: configparser==3.5.0; python_version == "2.7"
Requires-Dist: futures>=3.0.5; python_version == "2.7"
Requires-Dist: importlib==1.0.4; python_version == "2.7"
Requires-Dist: pywin32>=220; sys_platform == "win32"
Requires-Dist: win-unicode-console; sys_platform == "win32"
Provides-Extra: htrc
Requires-Dist: htrc-feature-reader>=1.92; extra == "htrc"
Requires-Dist: htrc; extra == "htrc"
Provides-Extra: inpho
Requires-Dist: inpho; extra == "inpho"
Requires-Dist: sqlalchemy; extra == "inpho"
